{
  "questIDHigh:4": 0,
  "preRequisites:9": {
    "0:10": {
      "questIDHigh:4": 0,
      "questIDLow:4": 2347
    }
  },
  "questIDLow:4": 2348,
  "properties:10": {
    "betterquesting:10": {
      "snd_complete:8": "random.levelup",
      "taskLogic:8": "AND",
      "partySingleReward:1": 0,
      "visibility:8": "NORMAL",
      "isMain:1": 0,
      "simultaneous:1": 0,
      "icon:10": {
        "id:8": "witchery:ingredient",
        "Count:3": 1,
        "Damage:2": 141,
        "OreDict:8": ""
      },
      "snd_update:8": "random.levelup",
      "repeatTime:3": -1,
      "globalShare:1": 1,
      "questLogic:8": "AND",
      "repeat_relative:1": 1,
      "name:8": "Lord of Torment",
      "isGlobal:1": 0,
      "lockedProgress:1": 0,
      "autoClaim:1": 0,
      "isSilent:1": 0,
      "desc:8": "A Lord of Torment is a mighty demonic being that is able to create prisons to Torment its victims.\n\nThose foolish enough to summon one of these creatures must prepare for an arduous fight.\n\nA Lord of Torment may only be summoned using the Ritual outlined in a Torment Scroll. \nThese scrolls are hard to come by, but it is rumored that well treated Flame Imps have occasionally given them up.\n\nConsuming the Soul of a Torment Demon grants the ability to Torment others.\n\nIf you are very unlucky and the Lord of Torment disappears when entering the Torment dimension, use the Egg and spawn another one."
    }
  },
  "tasks:9": {
    "0:10": {
      "partialMatch:1": 1,
      "autoConsume:1": 0,
      "groupDetect:1": 0,
      "ignoreNBT:1": 0,
      "index:3": 0,
      "consume:1": 0,
      "requiredItems:9": {
        "0:10": {
          "id:8": "witchery:ingredient",
          "Count:3": 1,
          "Damage:2": 141,
          "OreDict:8": ""
        }
      },
      "taskID:8": "bq_standard:retrieval"
    },
    "1:10": {
      "visible:1": 0,
      "invert:1": 0,
      "range:3": -1,
      "index:3": 1,
      "structure:8": "",
      "hideInfo:1": 0,
      "posX:3": 0,
      "posY:3": 0,
      "posZ:3": 0,
      "biome:3": -1,
      "name:8": "The real Hell",
      "dimension:3": 56,
      "taxiCabDist:1": 0,
      "taskID:8": "bq_standard:location"
    }
  },
  "rewards:9": {
    "0:10": {
      "rewardID:8": "bq_standard:choice",
      "index:3": 0,
      "choices:9": {
        "0:10": {
          "id:8": "witchery:ingredient",
          "Count:3": 2,
          "Damage:2": 23,
          "OreDict:8": ""
        },
        "1:10": {
          "id:8": "witchery:ingredient",
          "Count:3": 5,
          "Damage:2": 38,
          "OreDict:8": ""
        },
        "2:10": {
          "id:8": "minecraft:spawn_egg",
          "Count:3": 1,
          "Damage:2": 6412,
          "OreDict:8": ""
        },
        "3:10": {
          "id:8": "enhancedlootbags:lootbag",
          "Count:3": 1,
          "Damage:2": 55,
          "OreDict:8": ""
        }
      }
    },
    "1:10": {
      "rewardID:8": "bq_standard:item",
      "index:3": 1,
      "rewards:9": {
        "0:10": {
          "id:8": "dreamcraft:item.CoinSurvivorII",
          "Count:3": 5,
          "Damage:2": 0,
          "OreDict:8": ""
        },
        "1:10": {
          "id:8": "dreamcraft:item.CoinWitchII",
          "Count:3": 5,
          "Damage:2": 0,
          "OreDict:8": ""
        },
        "2:10": {
          "id:8": "dreamcraft:item.CoinDarkWizardII",
          "Count:3": 5,
          "Damage:2": 0,
          "OreDict:8": ""
        }
      }
    }
  }
}