{
  "preRequisites:9": {
    "0:10": {
      "questIDHigh:4": -6376998921577086813,
      "questIDLow:4": -8222665240642675552
    },
    "1:10": {
      "questIDHigh:4": 6871186703039940952,
      "questIDLow:4": -5095508056809418717
    }
  },
  "properties:10": {
    "betterquesting:10": {
      "autoClaim:1": 0,
      "desc:8": "Now with access to Maahes you can finally start making §5§lBiocatalyzed Propulsion Fluid§r. \n\nBPF is a superior fuel for the §9Spinmatron-2737§r, granting an additional §2§l1.25x§r parallels and allowing you to finally have access to §a§lHeavy mode§r dependent recipes.\n\n[note]If you happen to be avoiding rockets; check out the §nLumipod Sapling§r recipe[/note]",
      "globalShare:1": 0,
      "icon:10": {
        "Count:3": 1,
        "Damage:2": 30166,
        "OreDict:8": "",
        "id:8": "gregtech:gt.metaitem.01"
      },
      "isMain:1": 0,
      "isSilent:1": 0,
      "lockedProgress:1": 0,
      "name:8": "Biocatalyzed Propulsion Fluid",
      "questLogic:8": "AND",
      "repeatTime:3": -1,
      "repeat_relative:1": 1,
      "simultaneous:1": 0,
      "snd_complete:8": "random.levelup",
      "snd_update:8": "random.levelup",
      "taskLogic:8": "AND",
      "visibility:8": "NORMAL"
    }
  },
  "questIDHigh:4": -6743958815604650667,
  "questIDLow:4": -5495064271200344269,
  "rewards:9": {},
  "tasks:9": {
    "0:10": {
      "autoConsume:1": 0,
      "consume:1": 0,
      "groupDetect:1": 0,
      "ignoreNBT:1": 1,
      "index:3": 0,
      "partialMatch:1": 1,
      "requiredItems:9": {
        "0:10": {
          "Count:3": 1,
          "Damage:2": 30166,
          "OreDict:8": "",
          "id:8": "gregtech:gt.metaitem.01"
        }
      },
      "taskID:8": "bq_standard:retrieval"
    }
  }
}