{
  "preRequisites:9": {
    "0:10": {
      "questIDHigh:4": 0,
      "questIDLow:4": 1598
    }
  },
  "properties:10": {
    "betterquesting:10": {
      "autoClaim:1": 0,
      "completion_animation:8": "default",
      "completion_particle:8": "default",
      "confetti_icon:10": {
        "Count:3": 0,
        "Damage:2": 0,
        "OreDict:8": "",
        "id:8": "minecraft:stick"
      },
      "countAsQuest:1": 1,
      "desc:8": "Sustainability. It\u0027s not the name of the game... but it could be!\n\nIf you\u0027ve ever wanted to generate many chemicals from a single source, you\u0027ve probably looked at Oil or Benzene. However, there\u0027s also the Algae Farm.\n\nEach tier, starting from ULV (at 50s per batch) through IV (25s per batch), reduces the time it takes to produce Algae by about 5 seconds, and then beyond that each tier will cut the duration in half. The production time can also randomly double or triple, but this happens relatively rarely.\n\nEach tier increase also adds to the amount of Algae you get in a single cycle, as well as the type of Algae produced. Each cycle gives out an exact amount as well as a bonus amount 10% of the time. The Algae Farm also accepts Compost, which you can make from the algae itself, to boost the multi\u0027s tier by one. This might be expensive at the start, but it\u0027s heavily recommended in most cases. You can get regular Algae and Green Algae starting at ULV; Brown Algae starts appearing at HV, Golden-Brown Algae at EV, and Red Algae at IV, though higher tier algae appears in very small quantities at first.\n\nTo find out more about the exact output quantities and timings, please see the wiki: [url]https://wiki.gtnewhorizons.com/wiki/Algae_Farm[/url]\n\nThe Algae can be used for various chemicals like Methane, Ammonia, Sulfuric Acid, Sodium Carbonate, Ethylene, Lithium Chloride, and even some power-generating fluids. You typically need a Chemical Plant for that. In IV tier you can also combine Green Algae with Glowstone to get Glowing Coral and make Sunnarium from that. If you\u0027re curious about all the processing chains, look them up on NEI: quests to cover them are coming up, possibly with more recipes that don\u0027t need the Chemical Plant.",
      "globalShare:1": 0,
      "icon:10": {
        "Count:3": 1,
        "Damage:2": 15545,
        "OreDict:8": "",
        "id:8": "gregtech:gt.blockmachines"
      },
      "isMain:1": 0,
      "isSilent:1": 0,
      "lockedProgress:1": 0,
      "name:8": "§6§lAlgae Pond",
      "notification_duration:5": -1.0,
      "notification_effect:3": -1,
      "notification_fade_in:5": -1.0,
      "notification_fade_out:5": -1.0,
      "notification_icon_offset_y:3": -2147483648,
      "notification_icon_scale:5": -1.0,
      "notification_pos_x:3": -2147483648,
      "notification_pos_y:3": -2147483648,
      "notification_show_icon:8": "default",
      "notification_style:8": "default",
      "notification_subtitle:8": "",
      "notification_subtitle_scale:5": -1.0,
      "notification_title:8": "",
      "notification_title_scale:5": -1.0,
      "particle_count:3": -1,
      "questLogic:8": "AND",
      "repeatTime:3": -1,
      "repeat_relative:1": 1,
      "simultaneous:1": 0,
      "snd_complete:8": "random.levelup",
      "snd_update:8": "random.levelup",
      "taskLogic:8": "AND",
      "visibility:8": "NORMAL"
    }
  },
  "questIDHigh:4": 1067327358665575267,
  "questIDLow:4": -8996825125550293613,
  "rewards:9": {
    "0:10": {
      "choices:9": {
        "0:10": {
          "Count:3": 1,
          "Damage:2": 0,
          "OreDict:8": "",
          "id:8": "miscutils:item.BasicAgrichemItem"
        },
        "1:10": {
          "Count:3": 1,
          "Damage:2": 1,
          "OreDict:8": "",
          "id:8": "miscutils:item.BasicAgrichemItem"
        },
        "2:10": {
          "Count:3": 1,
          "Damage:2": 2,
          "OreDict:8": "",
          "id:8": "miscutils:item.BasicAgrichemItem"
        },
        "3:10": {
          "Count:3": 1,
          "Damage:2": 3,
          "OreDict:8": "",
          "id:8": "miscutils:item.BasicAgrichemItem"
        },
        "4:10": {
          "Count:3": 1,
          "Damage:2": 4,
          "OreDict:8": "",
          "id:8": "miscutils:item.BasicAgrichemItem"
        }
      },
      "ignoreDisabled:1": 0,
      "index:3": 0,
      "rewardID:8": "bq_standard:choice"
    },
    "1:10": {
      "ignoreDisabled:1": 0,
      "index:3": 1,
      "rewardID:8": "bq_standard:item",
      "rewards:9": {
        "0:10": {
          "Count:3": 2,
          "Damage:2": 5,
          "OreDict:8": "",
          "id:8": "enhancedlootbags:lootbag"
        }
      }
    }
  },
  "tasks:9": {
    "0:10": {
      "autoConsume:1": 0,
      "consume:1": 0,
      "groupDetect:1": 0,
      "ignoreNBT:1": 1,
      "index:3": 0,
      "partialMatch:1": 1,
      "requireOnlyOneItem:1": 0,
      "requiredItems:9": {
        "0:10": {
          "Count:3": 1,
          "Damage:2": 15545,
          "OreDict:8": "",
          "id:8": "gregtech:gt.blockmachines"
        }
      },
      "taskID:8": "bq_standard:retrieval"
    },
    "1:10": {
      "autoConsume:1": 0,
      "consume:1": 0,
      "groupDetect:1": 0,
      "ignoreNBT:1": 1,
      "index:3": 1,
      "partialMatch:1": 1,
      "requireOnlyOneItem:1": 0,
      "requiredItems:9": {
        "0:10": {
          "Count:3": 68,
          "Damage:2": 0,
          "OreDict:8": "",
          "id:8": "bartworks:BW_TieredGlass"
        },
        "1:10": {
          "Count:3": 23,
          "Damage:2": 15,
          "OreDict:8": "",
          "id:8": "gregtech:gt.blockcasings12"
        },
        "2:10": {
          "Count:3": 6,
          "Damage:2": 306,
          "OreDict:8": "",
          "id:8": "gregtech:gt.blockframes"
        },
        "3:10": {
          "Count:3": 5,
          "Damage:2": 11,
          "OreDict:8": "",
          "id:8": "gregtech:gt.blockcasings3"
        }
      },
      "taskID:8": "bq_standard:optional_retrieval"
    },
    "2:10": {
      "autoConsume:1": 0,
      "consume:1": 0,
      "groupDetect:1": 0,
      "ignoreNBT:1": 1,
      "index:3": 2,
      "partialMatch:1": 1,
      "requireOnlyOneItem:1": 0,
      "requiredItems:9": {
        "0:10": {
          "Count:3": 1,
          "Damage:2": 31071,
          "OreDict:8": "",
          "id:8": "gregtech:gt.blockmachines"
        }
      },
      "taskID:8": "bq_standard:optional_retrieval"
    }
  }
}