{
  "preRequisites:9": {
    "0:10": {
      "questIDHigh:4": -3386790291524794961,
      "questIDLow:4": -5427043695285873838,
      "type:1": 2
    }
  },
  "properties:10": {
    "betterquesting:10": {
      "autoClaim:1": 0,
      "desc:8": "Each crop has a set of preferred biome tags. These can be viewed in NEI along with the other growth requirements. \r\n\nHaving the proper biome tags will provide a significant Nutrient Point boost to your crops (§l+14 Points§r per tag).\n\nYou can only benefit from up to 2 biome tags (§l+28 Points§r).\r\n\nIt is possible to emulate a single preferred biome tag by planting your crops in a high-humidity location. The bonus scales linearly with humidity between 50% and 80%. Values below 50% provide no bonus, while values above 80% will hit the cap at an equivalent of 1 preferred biome tag (§l+14 Points).\n\r\n§l§rIf any favored biome tag is present in the current biome, the high humidity bonus will be ignored.\r\n\n\nThe Nature\u0027s Compass will allow you to view the tags of each biome as subtext within its menu.",
      "globalShare:1": 0,
      "icon:10": {
        "Count:3": 1,
        "Damage:2": 0,
        "OreDict:8": "",
        "id:8": "naturescompass:NaturesCompass",
        "tag:10": {}
      },
      "isMain:1": 0,
      "isSilent:1": 0,
      "lockedProgress:1": 0,
      "name:8": "Environmental Preferences",
      "questLogic:8": "AND",
      "repeatTime:3": -1,
      "repeat_relative:1": 1,
      "simultaneous:1": 0,
      "snd_complete:8": "random.levelup",
      "snd_update:8": "random.levelup",
      "taskLogic:8": "AND",
      "visibility:8": "NORMAL"
    }
  },
  "questIDHigh:4": 2164260398161413693,
  "questIDLow:4": -8567606770791078099,
  "rewards:9": {},
  "tasks:9": {
    "0:10": {
      "index:3": 0,
      "taskID:8": "bq_standard:checkbox"
    }
  }
}